todo_cli/__init__.py
todo_cli/cli.py
todo_cli/core.py
todo_cli/storage.py
todo_cli/utils.py
todos_cmd-0.1.1.dist-info/LICENSE
todos_cmd-0.1.1.dist-info/METADATA
todos_cmd-0.1.1.dist-info/WHEEL
todos_cmd-0.1.1.dist-info/entry_points.txt
todos_cmd-0.1.1.dist-info/top_level.txt
todos_cmd-0.1.1.dist-info/RECORD
