Metadata-Version: 2.1
Name: todos-cmd
Version: 0.1.1
Summary: A powerful CLI Todo App with search, tagging, priority, and due date support
Home-page: https://github.com/rajat-gith/todo-cli
Author: Rajat Nayak
License: MIT
Classifier: Programming Language :: Python :: 3
Classifier: Environment :: Console
Classifier: Operating System :: OS Independent
Requires-Python: >=3.7
License-File: LICENSE
Requires-Dist: click>=8.0
Requires-Dist: colorama>=0.4
